pylibrelinkup/__init__.py
pylibrelinkup/api_url.py
pylibrelinkup/data_types.py
pylibrelinkup/decorators.py
pylibrelinkup/exceptions.py
pylibrelinkup/py.typed
pylibrelinkup/pylibrelinkup.py
pylibrelinkup/utilities.py
pylibrelinkup/models/__init__.py
pylibrelinkup/models/base.py
pylibrelinkup/models/config.py
pylibrelinkup/models/connection.py
pylibrelinkup/models/data.py
pylibrelinkup/models/hardware.py
pylibrelinkup/models/login.py
pylibrelinkup-0.9.1.dist-info/licenses/LICENSE
pylibrelinkup-0.9.1.dist-info/METADATA
pylibrelinkup-0.9.1.dist-info/WHEEL
pylibrelinkup-0.9.1.dist-info/top_level.txt
pylibrelinkup-0.9.1.dist-info/RECORD
