Metadata-Version: 2.4
Name: pylibrelinkup
Version: 0.9.1
Summary: A client for the Abbott LibreLinkUp API
Author-email: Rob Berwick <rob.berwick@gmail.com>
License: MIT License
Project-URL: Homepage, https://github.com/robberwick/pylibrelinkup
Project-URL: Issues, https://github.com/robberwick/pylibrelinkup/issues
Project-URL: Documentation, https://pylibrelinkup.readthedocs.io/
Keywords: librelink,librelinkup,abbott,diabetes,glucose,api,client,health,medical,blood-sugar,continuous-glucose-monitoring,cgm
Classifier: Programming Language :: Python :: 3
Classifier: License :: OSI Approved :: MIT License
Classifier: Operating System :: OS Independent
Requires-Python: >=3.11
License-File: LICENSE
Requires-Dist: requests>=2.31.0
Requires-Dist: pydantic>=2.5.0
Provides-Extra: docs
Requires-Dist: sphinx<8.1,>=8.0.2; extra == "docs"
Requires-Dist: sphinx-rtd-theme<3.1,>=3.0.0rc4; extra == "docs"
Requires-Dist: sphinx-autobuild<2025.0,>=2024.10.3; extra == "docs"
Requires-Dist: sphinx-autodoc-typehints<2.5,>=2.4.4; extra == "docs"
Requires-Dist: autodoc_pydantic<2.3,>=2.2.0; extra == "docs"
Requires-Dist: enum-tools[sphinx]<0.13,>=0.12.0; extra == "docs"
Requires-Dist: setuptools_scm<8.2,>=8.1.0; extra == "docs"
Provides-Extra: dev
Requires-Dist: black; extra == "dev"
Requires-Dist: isort; extra == "dev"
Requires-Dist: pre-commit; extra == "dev"
Requires-Dist: mypy; extra == "dev"
Requires-Dist: flake8; extra == "dev"
Requires-Dist: types-requests; extra == "dev"
Provides-Extra: test
Requires-Dist: pytest; extra == "test"
Requires-Dist: pytest-cov; extra == "test"
Requires-Dist: pytest-mock; extra == "test"
Requires-Dist: polyfactory; extra == "test"
Requires-Dist: responses; extra == "test"
Dynamic: license-file
